LICENSE
MANIFEST.in
README.rst
setup.py
smpp/__init__.py
smpp/esme.py
smpp/pdu_builder.py
smpp/pdu_inspector.py
smpp/smsc.py
smpp_server.egg-info/PKG-INFO
smpp_server.egg-info/SOURCES.txt
smpp_server.egg-info/dependency_links.txt
smpp_server.egg-info/pbr.json
smpp_server.egg-info/top_level.txt