Metadata-Version: 1.1
Name: smpp-server
Version: 0.1.0
Summary: Python SMPP Library
Home-page: https://github.com/komuW/smpp_server
Author: komuW
Author-email: komuw05@gmail.com
License: BSD
Platform: UNKNOWN
Classifier: Development Status :: 4 - Beta
Classifier: Intended Audience :: Developers
Classifier: License :: OSI Approved :: BSD License
Classifier: Operating System :: OS Independent
Classifier: Programming Language :: Python
Classifier: Topic :: Software Development :: Libraries :: Python Modules
